{
  "updatedAt": "2026-07-15 20:05:11 KST",
  "updatedTime": "20:05",
  "kospi": {
    "price": 7284.41,
    "change": 427.58,
    "changePct": 6.24,
    "pct5": 0.52
  },
  "market": {
    "sox": {
      "name": "필라델피아 반도체",
      "price": 12661.93,
      "pct": 2.54
    },
    "nasdaq": {
      "name": "나스닥 선물",
      "price": 29923.5,
      "pct": 0.45
    },
    "fx": {
      "name": "원/달러 환율",
      "price": 1493.8,
      "pct": 0.37
    },
    "vix": {
      "name": "공포지수(VIX)",
      "price": 16.35,
      "pct": -0.91
    },
    "tnx": {
      "name": "미국 10년물 금리",
      "price": 4.58,
      "pct": -0.52
    },
    "dxy": {
      "name": "달러인덱스",
      "price": 101.0,
      "pct": 0.08
    },
    "cny": {
      "name": "위안/달러",
      "price": 6.76,
      "pct": 0.0
    },
    "tsmc": {
      "name": "TSMC",
      "price": 420.39,
      "pct": -0.28
    },
    "nvda": {
      "name": "엔비디아",
      "price": 211.8,
      "pct": 4.06
    },
    "mu": {
      "name": "마이크론",
      "price": 983.12,
      "pct": 4.92
    },
    "oil": {
      "name": "WTI 유가",
      "price": 79.99,
      "pct": 0.82
    },
    "copper": {
      "name": "구리",
      "price": 6.36,
      "pct": -0.28
    },
    "gold": {
      "name": "금",
      "price": 4034.2,
      "pct": -0.87
    },
    "kospi": {
      "name": "코스피",
      "price": 7284.41,
      "pct": 6.24
    },
    "ewy": {
      "name": "한국ETF(MSCI)",
      "price": 176.98,
      "pct": 5.33
    },
    "xlf": {
      "name": "미국 금융ETF",
      "price": 56.18,
      "pct": 0.2
    },
    "summary": {
      "mood": "favorable",
      "label": "우호적",
      "score": 3.2,
      "advice": "미국 기술주 강세. 갭상승 가능성. 추격매수는 신중히, 눌림목 기다리는 것도 방법이에요.",
      "buyThreshold": 5,
      "thresholdNote": "시장 우호 — 문턱 5로 완화 (반 박자 빠른 진입)",
      "cnyNote": "위안은 안정인데 원화만 약세 — 한국 고유 악재 가능성. 외국인 이탈 신호일 수 있어 더 주의.",
      "tsmcNote": "SOX 강세지만 TSMC는 약세(-0.28%) — 파운드리 부진. 삼성·하이닉스 신중."
    },
    "forecast": {
      "kospi": {
        "dir": "상승",
        "strength": "중",
        "color": "#00c896",
        "bias": 1.0,
        "low": 0.5,
        "high": 1.5,
        "text": "상승 경향 중 (대략 +1.0% 안팎)"
      },
      "semi": {
        "dir": "상승",
        "strength": "중",
        "color": "#00c896",
        "bias": 1.4,
        "low": 0.8,
        "high": 2.0,
        "text": "상승 경향 중 (SOX +2.54% · TSMC -0.28%)"
      },
      "disclaimer": "야간 해외지표 기반 경향일 뿐, 갭은 자주 빗나가요. 진입은 시장 방향이 아니라 종목 자리(지지·수급)로 판단하세요."
    },
    "crashRisk": {
      "level": "평이",
      "score": 0,
      "color": "#10b981",
      "reasons": [],
      "advice": "",
      "alert": false
    },
    "expiry": {
      "warn": false,
      "level": "",
      "text": ""
    }
  },
  "stocks": [
    {
      "code": "000660",
      "price": 2082000,
      "change": 169000,
      "changePct": 8.83,
      "high52w": 2987000,
      "low52w": 245000,
      "opinion": "중립",
      "score": 1,
      "source": "네이버 금융",
      "intradayFlow": null,
      "micro": null,
      "program": null,
      "flowTurnaround": false,
      "spark": [
        2685000,
        2764000,
        2919000,
        2555000,
        2621000,
        2917000,
        2673000,
        2628000,
        2650000,
        2560000,
        2187000,
        2425000,
        2343000,
        2201000,
        2076000,
        2186000,
        2180000,
        1845000,
        1913000,
        2082000
      ],
      "nuance": "관찰 — 신호 부족",
      "buyTrack": {
        "type": "none"
      },
      "buyThreshold": {
        "buy": 5,
        "sell": -5,
        "label": "시장 우호 → 완화",
        "drivers": [
          {
            "k": "약세 다이버전스",
            "v": -4
          },
          {
            "k": "MACD",
            "v": -2
          },
          {
            "k": "OBV",
            "v": 2
          },
          {
            "k": "스토캐RSI",
            "v": 2
          }
        ]
      },
      "scoreDrivers": [
        {
          "k": "약세 다이버전스",
          "v": -4
        },
        {
          "k": "MACD",
          "v": -2
        },
        {
          "k": "OBV",
          "v": 2
        },
        {
          "k": "스토캐RSI",
          "v": 2
        }
      ],
      "macro": {
        "adj": 2.0,
        "parts": [
          "SOX +2.54% → +1.0",
          "마이크론 +4.92% → +1.2",
          "NVDA +4.06% → +0.6"
        ]
      },
      "sigReasons": {
        "buy": [
          "OBV 상승(매집)",
          "스토캐스틱RSI 과매도 반등",
          "매크로 +2.0"
        ],
        "sell": [
          "하락 다이버전스",
          "MACD 하락(데드)",
          "일목 매도"
        ]
      },
      "contrarian": "",
      "profitTaking": "",
      "marginCallRisk": "",
      "turnover": "🔄 물갈이 진행 — 개인 투매를 외국인·기관이 흡수 중",
      "chaseWarning": "",
      "marketBrake": "",
      "flowRead": "신호는 중립이고 외국인은 이탈 중이에요. │ 서두르지 말고 수급 방향 전환을 확인 후 대응.",
      "tradedAt": "2026-07-15",
      "fairValue": 3547917,
      "fairValueGap": 70.4,
      "fairValueComment": "증권사 목표가 대비 70.4% 상승여력",
      "fairValueDetail": {
        "basis": "목표주가",
        "target_price": 3547917,
        "current_per": 20.11,
        "cns_per": 6.58,
        "recomm": 4.0,
        "sector": "반도체",
        "sector_per": 20
      },
      "eps": 103521,
      "bps": 237789,
      "boll": {
        "upper": 3047202,
        "mid": 2420500,
        "lower": 1793798,
        "position": 23
      },
      "atr": {
        "atr": 257357,
        "pct": 12.36
      },
      "atrStopLoss": 1567286,
      "cmf": {
        "value": -0.145,
        "comment": "분산 우세 (조용한 이탈)"
      },
      "cmfBars": [
        0.42,
        -0.25,
        0.76,
        -0.91,
        0.34,
        0.41,
        -0.48,
        0.3,
        0.08,
        -0.48,
        -1.0,
        0.86,
        -0.5,
        -0.08,
        -1.0,
        0.06,
        -0.8,
        -0.96,
        0.82,
        -0.76
      ],
      "suggestedPrice": 0,
      "suggestedLabel": "해당없음",
      "targetPrice": 0,
      "targetPrice2": 0,
      "stopLoss": 0,
      "rsi": 45.8,
      "rsiComment": "중립",
      "macd": -2.714,
      "macdSignal": 1.351,
      "macdHist": -4.065,
      "macdComment": "데드크로스 — 하락 압력",
      "stoch": 33.6,
      "stochComment": "중립",
      "stochRsi": {
        "k": 13.7,
        "d": 9.1,
        "signal": "매수",
        "comment": "과매도 구간(14) — 반등 임박"
      },
      "divergence": {
        "bullish": false,
        "bearish": true,
        "signal": "매도",
        "comment": "약세 다이버전스 — 주가 ↑ / RSI ↓ (77→68)"
      },
      "ichimoku": {
        "tenkan": 2087500,
        "kijun": 2332500,
        "senkouA": 2210000,
        "senkouB": 2134000,
        "cloudTop": 2210000,
        "cloudBot": 2134000,
        "signal": "매도",
        "comment": "구름대 아래 + 전환선<기준선 — 강한 하락 추세"
      },
      "cci": {
        "value": -80.0,
        "signal": "중립",
        "comment": "중립(-80)"
      },
      "psar": {
        "psar": 2507952,
        "trend": "하락",
        "signal": "매도",
        "comment": "하락 추세 (저항선 ₩2,507,952)",
        "nearFlip": false
      },
      "valueSurge": {
        "ratio": 0.88,
        "surge": false,
        "comment": "거래대금 평이 (0.9배)"
      },
      "cautiousEntry": {
        "entry": false,
        "signals": [],
        "reason": "",
        "stopLoss": 0
      },
      "overheat": {
        "level": "none",
        "reasons": [],
        "color": "",
        "title": ""
      },
      "wr": -66.4,
      "wrComment": "중립",
      "mfi": 38.8,
      "mfiComment": "중립",
      "adx": {
        "adx": 59.2,
        "pdi": 10.2,
        "ndi": 39.7,
        "strength": "강한 추세"
      },
      "obv": {
        "obv": 78298122,
        "slope": 5.6,
        "trend": "상승"
      },
      "vwap": 2021716,
      "pivot": {
        "p": 1842333,
        "r1": 2006667,
        "r2": 2100333,
        "s1": 1748667,
        "s2": 1584333
      },
      "sma5": 2041200,
      "sma20": 2420500,
      "sma60": 2024533,
      "patterns": [],
      "contra": {
        "signals": [],
        "action": "현 신호 유효",
        "strength": 0
      },
      "fg": {
        "score": 50,
        "label": "중립",
        "color": "#9ab"
      },
      "ft": "외국인 2일 연속 순매수",
      "fc": "외국인 +331,145주 · 기관 +265,930주 (07/15 기준)",
      "volRatio": 1.0,
      "investor": {
        "foreign": 331145,
        "institution": 265930,
        "individual": -582862,
        "foreign5": -687313,
        "foreign20": -8576571,
        "foreign60": -22164289,
        "inst5": 790431,
        "inst20": -215726,
        "inst60": 3125471,
        "indiv5": -129146,
        "indiv20": 8578593,
        "indiv60": 18595739,
        "days": 5,
        "ndays": 60,
        "daily": [
          -209485,
          -768843,
          -704671,
          664541,
          331145
        ],
        "flowLabel": "최근 매수 전환",
        "dailyInst": [
          404365,
          204193,
          -781727,
          697670,
          265930
        ],
        "flowLabelInst": "꾸준히 매수",
        "dailyIndiv": [
          -179724,
          550090,
          1440630,
          -1357280,
          -582862
        ],
        "flowLabelIndiv": "최근 매도 전환",
        "foreignTrend": "외국인 2일 연속 순매수",
        "comment": "외국인 +331,145주 · 기관 +265,930주 (07/15 기준)",
        "holdRatio": "49.93%",
        "streak": 2,
        "date": "07/15"
      },
      "short": {
        "ratio": 0,
        "trend": "flat",
        "comment": "공매도 미제공",
        "days": 0
      },
      "fundamentals": {
        "revGrowth": 46.8,
        "opGrowth": 101.2,
        "roe": 44.15,
        "debtRatio": 45.95,
        "opMargin": 48.59,
        "fwdEpsGrowth": 436.5,
        "years": [
          "2023.12.",
          "2024.12.",
          "2025.12.",
          "2026.12."
        ],
        "grade": "✅ 실적 건전",
        "gradeColor": "#00e5a0",
        "comment": "실적이 주가를 받쳐줘요. 추정이익 +436% 성장 · 영업이익 +101% · ROE 44%",
        "rows": {
          "매출액": {
            "202312": 327657.0,
            "202412": 661930.0,
            "202512": 971467.0,
            "202612": 3553234.0
          },
          "영업이익": {
            "202312": -77303.0,
            "202412": 234673.0,
            "202512": 472063.0,
            "202612": 2742318.0
          },
          "ROE": {
            "202312": -15.61,
            "202412": 31.06,
            "202512": 44.15,
            "202612": 97.05
          },
          "부채비율": {
            "202312": 87.52,
            "202412": 62.15,
            "202512": 45.95,
            "202612": null
          }
        }
      },
      "creditRatio": 0,
      "weekly": {
        "opinion": "중립",
        "rsi": 59.8,
        "macd": 18.566,
        "macdSignal": 19.096,
        "comment": "주봉 RSI 59.8 · MACD 데드크로스"
      },
      "monthly": {
        "opinion": "중립",
        "rsi": 72.5,
        "macd": null,
        "macdSignal": null,
        "comment": "주봉 RSI 72.5 · MACD -",
        "timeframe": "월봉"
      },
      "relativeStrength": {
        "rs": 2.59,
        "comment": "KOSPI 대비 +2.59%p 강세",
        "strong": true,
        "indexLinked": false,
        "indexNote": ""
      },
      "breakout": {
        "nearHigh": false,
        "nearLow": false,
        "position": 67,
        "comment": "52주 중간 위치 (67%)"
      },
      "volSurge": {
        "surge": false,
        "ratio": 1.0,
        "comment": "거래량 평이 (1.0x)"
      },
      "news": [],
      "dart": [
        {
          "title": "기업설명회(IR)개최(안내공시)              ",
          "date": "20260715",
          "important": false,
          "corp": "SK하이닉스",
          "url": "https://dart.fss.or.kr/dsaf001/main.do?rcpNo=20260715800456"
        },
        {
          "title": "유상증자또는주식관련사채등의발행결과(자율공시)              ",
          "date": "20260715",
          "important": true,
          "corp": "SK하이닉스",
          "url": "https://dart.fss.or.kr/dsaf001/main.do?rcpNo=20260715800045"
        },
        {
          "title": "증권발행실적보고서",
          "date": "20260715",
          "important": true,
          "corp": "SK하이닉스",
          "url": "https://dart.fss.or.kr/dsaf001/main.do?rcpNo=20260715000004"
        },
        {
          "title": "주요사항보고서(해외증권시장주권등상장)",
          "date": "20260713",
          "important": true,
          "corp": "SK하이닉스",
          "url": "https://dart.fss.or.kr/dsaf001/main.do?rcpNo=20260713000324"
        },
        {
          "title": "투자설명서",
          "date": "20260710",
          "important": false,
          "corp": "SK하이닉스",
          "url": "https://dart.fss.or.kr/dsaf001/main.do?rcpNo=20260710000012"
        }
      ],
      "basis": [
        "RSI 45.8 · Williams%R -66.4 · MFI 38.8 — 지표 중립권",
        "외국인 +331,145주 · 기관 +265,930주 · OBV 상승",
        "주봉 중립 · 67%"
      ],
      "risk": [],
      "notes": [
        "주봉·일봉 동시 매수 신호 확인 후 진입",
        "외국인 순매수 전환 시 진입 검토",
        "공매도 감소 + 거래량 증가 조합 주시"
      ],
      "noChart": false
    },
    {
      "code": "005930",
      "price": 279500,
      "change": 16500,
      "changePct": 6.27,
      "high52w": 374500,
      "low52w": 62000,
      "opinion": "중립",
      "score": 2,
      "source": "네이버 금융",
      "intradayFlow": null,
      "micro": null,
      "program": null,
      "flowTurnaround": false,
      "spark": [
        362500,
        354000,
        353500,
        310000,
        340500,
        358500,
        339500,
        323000,
        334000,
        314500,
        286000,
        309500,
        318000,
        296000,
        277500,
        278000,
        285000,
        254500,
        263000,
        279500
      ],
      "nuance": "관찰 — 신호 부족",
      "buyTrack": {
        "type": "none"
      },
      "buyThreshold": {
        "buy": 5,
        "sell": -5,
        "label": "시장 우호 → 완화",
        "drivers": [
          {
            "k": "약세 다이버전스",
            "v": -4
          },
          {
            "k": "MACD",
            "v": -2
          },
          {
            "k": "OBV",
            "v": 2
          },
          {
            "k": "스토캐RSI",
            "v": 2
          }
        ]
      },
      "scoreDrivers": [
        {
          "k": "약세 다이버전스",
          "v": -4
        },
        {
          "k": "MACD",
          "v": -2
        },
        {
          "k": "OBV",
          "v": 2
        },
        {
          "k": "스토캐RSI",
          "v": 2
        }
      ],
      "macro": {
        "adj": 2.0,
        "parts": [
          "SOX +2.54% → +0.9",
          "마이크론 +4.92% → +1.0",
          "NVDA +4.06% → +0.4"
        ]
      },
      "sigReasons": {
        "buy": [
          "OBV 상승(매집)",
          "스토캐스틱RSI 과매도 반등",
          "매크로 +2.0"
        ],
        "sell": [
          "하락 다이버전스",
          "MACD 하락(데드)",
          "일목 매도"
        ]
      },
      "contrarian": "",
      "profitTaking": "",
      "marginCallRisk": "",
      "turnover": "",
      "chaseWarning": "",
      "marketBrake": "",
      "flowRead": "신호는 중립이나 외국인은 5일째 매집 중이에요. │ 수급은 우호적, 지지구간 확인하며 분할 접근.",
      "tradedAt": "2026-07-15",
      "fairValue": 513958,
      "fairValueGap": 83.9,
      "fairValueComment": "증권사 목표가 대비 83.9% 상승여력",
      "fairValueDetail": {
        "basis": "목표주가",
        "target_price": 513958,
        "current_per": 22.59,
        "cns_per": 5.99,
        "recomm": 4.04,
        "sector": "반도체",
        "sector_per": 15
      },
      "eps": 12372,
      "bps": 71907,
      "boll": {
        "upper": 376958,
        "mid": 311850,
        "lower": 246742,
        "position": 25
      },
      "atr": {
        "atr": 27214,
        "pct": 9.74
      },
      "atrStopLoss": 225072,
      "cmf": {
        "value": -0.063,
        "comment": "분산 우세 (조용한 이탈)"
      },
      "cmfBars": [
        0.95,
        -0.45,
        0.1,
        -1.0,
        0.96,
        0.24,
        0.03,
        -0.28,
        0.18,
        -0.78,
        -0.6,
        0.76,
        0.36,
        -0.17,
        -0.7,
        -0.12,
        -0.62,
        -0.92,
        0.39,
        0.13
      ],
      "suggestedPrice": 0,
      "suggestedLabel": "해당없음",
      "targetPrice": 0,
      "targetPrice2": 0,
      "stopLoss": 0,
      "rsi": 44.9,
      "rsiComment": "저점권",
      "macd": -4.0,
      "macdSignal": -1.389,
      "macdHist": -2.611,
      "macdComment": "데드크로스 — 하락 압력",
      "stoch": 29.7,
      "stochComment": "중립",
      "stochRsi": {
        "k": 17.3,
        "d": 9.6,
        "signal": "매수",
        "comment": "과매도 구간(17) — 반등 임박"
      },
      "divergence": {
        "bullish": false,
        "bearish": true,
        "signal": "매도",
        "comment": "약세 다이버전스 — 주가 ↑ / RSI ↓ (79→63)"
      },
      "ichimoku": {
        "tenkan": 286000,
        "kijun": 310750,
        "senkouA": 298375,
        "senkouB": 296500,
        "cloudTop": 298375,
        "cloudBot": 296500,
        "signal": "매도",
        "comment": "구름대 아래 + 전환선<기준선 — 강한 하락 추세"
      },
      "cci": {
        "value": -83.8,
        "signal": "중립",
        "comment": "중립(-84)"
      },
      "psar": {
        "psar": 321926,
        "trend": "하락",
        "signal": "매도",
        "comment": "하락 추세 (저항선 ₩321,926)",
        "nearFlip": false
      },
      "valueSurge": {
        "ratio": 0.73,
        "surge": false,
        "comment": "거래대금 평이 (0.7배)"
      },
      "cautiousEntry": {
        "entry": false,
        "signals": [],
        "reason": "",
        "stopLoss": 0
      },
      "overheat": {
        "level": "none",
        "reasons": [],
        "color": "",
        "title": ""
      },
      "wr": -70.3,
      "wrComment": "중립",
      "mfi": 30.6,
      "mfiComment": "중립",
      "adx": {
        "adx": 49.4,
        "pdi": 13.0,
        "ndi": 38.3,
        "strength": "강한 추세"
      },
      "obv": {
        "obv": 295684639,
        "slope": 22.9,
        "trend": "상승"
      },
      "vwap": 272490,
      "pivot": {
        "p": 260000,
        "r1": 273000,
        "r2": 283000,
        "s1": 250000,
        "s2": 237000
      },
      "sma5": 272000,
      "sma20": 311850,
      "sma60": 291658,
      "patterns": [],
      "contra": {
        "signals": [],
        "action": "현 신호 유효",
        "strength": 0
      },
      "fg": {
        "score": 50,
        "label": "중립",
        "color": "#9ab"
      },
      "ft": "외국인 순매수",
      "fc": "외국인 +1,799,843주 · 기관 -413,531주 (07/15 기준)",
      "volRatio": 0.81,
      "investor": {
        "foreign": 1799843,
        "institution": -413531,
        "individual": -1363799,
        "foreign5": 1425611,
        "foreign20": -45943873,
        "foreign60": -142186650,
        "inst5": 5087949,
        "inst20": 8408827,
        "inst60": 40595123,
        "indiv5": -5880845,
        "indiv20": 37085149,
        "indiv60": 96627902,
        "days": 5,
        "ndays": 60,
        "daily": [
          845552,
          625985,
          -716994,
          -1128775,
          1799843
        ],
        "flowLabel": "최근 매도 전환",
        "dailyInst": [
          1107761,
          2313745,
          -3246131,
          5326105,
          -413531
        ],
        "flowLabelInst": "꾸준히 매수",
        "dailyIndiv": [
          -1739937,
          -2851466,
          4206987,
          -4132630,
          -1363799
        ],
        "flowLabelIndiv": "꾸준히 매도",
        "foreignTrend": "외국인 순매수",
        "comment": "외국인 +1,799,843주 · 기관 -413,531주 (07/15 기준)",
        "holdRatio": "46.61%",
        "streak": 1,
        "date": "07/15"
      },
      "short": {
        "ratio": 0,
        "trend": "flat",
        "comment": "공매도 미제공",
        "days": 0
      },
      "fundamentals": {
        "revGrowth": 10.9,
        "opGrowth": 33.2,
        "roe": 10.85,
        "debtRatio": 29.94,
        "opMargin": 13.07,
        "fwdEpsGrowth": 610.9,
        "years": [
          "2023.12.",
          "2024.12.",
          "2025.12.",
          "2026.12."
        ],
        "grade": "✅ 실적 건전",
        "gradeColor": "#00e5a0",
        "comment": "실적이 주가를 받쳐줘요. 추정이익 +611% 성장 · 영업이익 +33% · ROE 11%",
        "rows": {
          "매출액": {
            "202312": 2589355.0,
            "202412": 3008709.0,
            "202512": 3336059.0,
            "202612": 7324732.0
          },
          "영업이익": {
            "202312": 65670.0,
            "202412": 327260.0,
            "202512": 436011.0,
            "202612": 3832404.0
          },
          "ROE": {
            "202312": 4.15,
            "202412": 9.03,
            "202512": 10.85,
            "202612": 54.54
          },
          "부채비율": {
            "202312": 25.36,
            "202412": 27.93,
            "202512": 29.94,
            "202612": null
          }
        }
      },
      "creditRatio": 0,
      "weekly": {
        "opinion": "중립",
        "rsi": 58.2,
        "macd": 13.581,
        "macdSignal": 15.752,
        "comment": "주봉 RSI 58.2 · MACD 데드크로스"
      },
      "monthly": {
        "opinion": "중립",
        "rsi": 69.5,
        "macd": null,
        "macdSignal": null,
        "comment": "주봉 RSI 69.5 · MACD -",
        "timeframe": "월봉"
      },
      "relativeStrength": {
        "rs": 0.03,
        "comment": "KOSPI 대비 중립",
        "strong": true,
        "indexLinked": true,
        "indexNote": "📐 지수 동조 — 코스피와 거의 같이 상승 중. 종목 자체 재료보다 지수 연계 거래(ETF·선물·프로그램)에 휘둘리는 흐름일 수 있어요. 지수가 진정되면 종목도 제자리 찾을 가능성."
      },
      "breakout": {
        "nearHigh": false,
        "nearLow": false,
        "position": 70,
        "comment": "52주 중간 위치 (70%)"
      },
      "volSurge": {
        "surge": false,
        "ratio": 0.81,
        "comment": "거래량 평이 (0.81x)"
      },
      "news": [],
      "dart": [
        {
          "title": "임원ㆍ주요주주특정증권등소유상황보고서",
          "date": "20260715",
          "important": false,
          "corp": "삼성전자",
          "url": "https://dart.fss.or.kr/dsaf001/main.do?rcpNo=20260715000412"
        },
        {
          "title": "[기재정정]임원ㆍ주요주주특정증권등소유상황보고서",
          "date": "20260715",
          "important": false,
          "corp": "삼성전자",
          "url": "https://dart.fss.or.kr/dsaf001/main.do?rcpNo=20260715000380"
        },
        {
          "title": "임원ㆍ주요주주특정증권등소유상황보고서",
          "date": "20260715",
          "important": false,
          "corp": "삼성전자",
          "url": "https://dart.fss.or.kr/dsaf001/main.do?rcpNo=20260715000139"
        },
        {
          "title": "임원ㆍ주요주주특정증권등소유상황보고서",
          "date": "20260714",
          "important": false,
          "corp": "삼성전자",
          "url": "https://dart.fss.or.kr/dsaf001/main.do?rcpNo=20260714000175"
        },
        {
          "title": "주요사항보고서(자기주식처분결정)",
          "date": "20260713",
          "important": true,
          "corp": "삼성전자",
          "url": "https://dart.fss.or.kr/dsaf001/main.do?rcpNo=20260713000395"
        }
      ],
      "basis": [
        "RSI 44.9 · Williams%R -70.3 · MFI 30.6 — 지표 중립권",
        "외국인 +1,799,843주 · 기관 -413,531주 · OBV 상승",
        "주봉 중립 · 70%"
      ],
      "risk": [],
      "notes": [
        "주봉·일봉 동시 매수 신호 확인 후 진입",
        "외국인 순매수 전환 시 진입 검토",
        "공매도 감소 + 거래량 증가 조합 주시"
      ],
      "noChart": false
    },
    {
      "code": "066570",
      "price": 194000,
      "change": 8600,
      "changePct": 4.64,
      "high52w": 438000,
      "low52w": 72000,
      "opinion": "중립",
      "score": 2,
      "source": "네이버 금융",
      "intradayFlow": null,
      "micro": null,
      "program": null,
      "flowTurnaround": false,
      "spark": [
        228500,
        211500,
        227500,
        202000,
        204500,
        203000,
        195900,
        196700,
        203000,
        193300,
        192300,
        191000,
        185700,
        189100,
        195800,
        178000,
        182400,
        185600,
        185400,
        194000
      ],
      "nuance": "관찰 — 신호 부족",
      "buyTrack": {
        "type": "none"
      },
      "buyThreshold": {
        "buy": 5,
        "sell": -5,
        "label": "시장 우호 → 완화",
        "drivers": [
          {
            "k": "MACD",
            "v": -2
          },
          {
            "k": "OBV",
            "v": 2
          },
          {
            "k": "일목",
            "v": -2
          },
          {
            "k": "ADX",
            "v": 1
          }
        ]
      },
      "scoreDrivers": [
        {
          "k": "MACD",
          "v": -2
        },
        {
          "k": "OBV",
          "v": 2
        },
        {
          "k": "일목",
          "v": -2
        },
        {
          "k": "ADX",
          "v": 1
        }
      ],
      "macro": {
        "adj": 0.0,
        "parts": []
      },
      "sigReasons": {
        "buy": [
          "OBV 상승(매집)",
          "52주 하단(33%)"
        ],
        "sell": [
          "MACD 하락(데드)",
          "일목 매도"
        ]
      },
      "contrarian": "",
      "profitTaking": "",
      "marginCallRisk": "",
      "turnover": "🔄 물갈이 진행 — 개인 투매를 외국인·기관이 흡수 중",
      "chaseWarning": "",
      "marketBrake": "",
      "flowRead": "신호는 중립이나 외국인은 5일째 매집 중이에요. │ 수급은 우호적, 지지구간 확인하며 분할 접근.",
      "tradedAt": "2026-07-15",
      "fairValue": 218250,
      "fairValueGap": 12.5,
      "fairValueComment": "증권사 목표가 대비 12.5% 상승여력",
      "fairValueDetail": {
        "basis": "목표주가",
        "target_price": 218250,
        "current_per": 35.79,
        "cns_per": 15.78,
        "recomm": 4.0,
        "sector": "가전/전장",
        "sector_per": 18
      },
      "eps": 5420,
      "bps": 142232,
      "boll": {
        "upper": 223325,
        "mid": 197260,
        "lower": 171195,
        "position": 44
      },
      "atr": {
        "atr": 15236,
        "pct": 7.85
      },
      "atrStopLoss": 163528,
      "cmf": {
        "value": -0.117,
        "comment": "분산 우세 (조용한 이탈)"
      },
      "cmfBars": [
        -0.69,
        -0.5,
        -0.37,
        -0.93,
        0.12,
        -0.5,
        0.4,
        0.7,
        -0.1,
        -0.5,
        0.24,
        0.96,
        -0.34,
        1.0,
        -0.04,
        -0.74,
        0.05,
        -0.85,
        0.52,
        0.05
      ],
      "suggestedPrice": 0,
      "suggestedLabel": "해당없음",
      "targetPrice": 0,
      "targetPrice2": 0,
      "stopLoss": 0,
      "rsi": 46.5,
      "rsiComment": "중립",
      "macd": -4.765,
      "macdSignal": -4.322,
      "macdHist": -0.443,
      "macdComment": "데드크로스 — 하락 압력",
      "stoch": 56.7,
      "stochComment": "중립",
      "stochRsi": {
        "k": 70.8,
        "d": 49.6,
        "signal": "중립",
        "comment": "K 71 / D 50"
      },
      "divergence": null,
      "ichimoku": {
        "tenkan": 191750,
        "kijun": 218500,
        "senkouA": 205125,
        "senkouB": 286300,
        "cloudTop": 286300,
        "cloudBot": 205125,
        "signal": "매도",
        "comment": "구름대 아래 + 전환선<기준선 — 강한 하락 추세"
      },
      "cci": {
        "value": -25.3,
        "signal": "중립",
        "comment": "중립(-25)"
      },
      "psar": {
        "psar": 175800,
        "trend": "상승",
        "signal": "매수",
        "comment": "상승 추세 유지 (손절선 ₩175,800)",
        "nearFlip": false
      },
      "valueSurge": {
        "ratio": 0.73,
        "surge": false,
        "comment": "거래대금 평이 (0.7배)"
      },
      "cautiousEntry": {
        "entry": false,
        "signals": [],
        "reason": "",
        "stopLoss": 0
      },
      "overheat": {
        "level": "none",
        "reasons": [],
        "color": "",
        "title": ""
      },
      "wr": -43.3,
      "wrComment": "중립",
      "mfi": 45.6,
      "mfiComment": "중립",
      "adx": {
        "adx": 2.6,
        "pdi": 28.5,
        "ndi": 30.0,
        "strength": "추세 없음(횡보)"
      },
      "obv": {
        "obv": 40192811,
        "slope": 9.7,
        "trend": "상승"
      },
      "vwap": 187295,
      "pivot": {
        "p": 183200,
        "r1": 190600,
        "r2": 195800,
        "s1": 178000,
        "s2": 170600
      },
      "sma5": 185080,
      "sma20": 197260,
      "sma60": 203517,
      "patterns": [],
      "contra": {
        "signals": [],
        "action": "현 신호 유효",
        "strength": 0
      },
      "fg": {
        "score": 49,
        "label": "중립",
        "color": "#9ab"
      },
      "ft": "외국인 4일 연속 순매수",
      "fc": "외국인 +131,282주 · 기관 +93,873주 (07/15 기준)",
      "volRatio": 0.75,
      "investor": {
        "foreign": 131282,
        "institution": 93873,
        "individual": -220714,
        "foreign5": 74365,
        "foreign20": 600394,
        "foreign60": -7347207,
        "inst5": 401360,
        "inst20": 644116,
        "inst60": 1411617,
        "indiv5": -461677,
        "indiv20": -1203412,
        "indiv60": 5338689,
        "days": 5,
        "ndays": 60,
        "daily": [
          -409382,
          268125,
          33607,
          50733,
          131282
        ],
        "flowLabel": "최근 매수 전환",
        "dailyInst": [
          40912,
          92188,
          26157,
          148230,
          93873
        ],
        "flowLabelInst": "꾸준히 매수",
        "dailyIndiv": [
          369303,
          -359553,
          -50330,
          -200383,
          -220714
        ],
        "flowLabelIndiv": "최근 매도 전환",
        "foreignTrend": "외국인 4일 연속 순매수",
        "comment": "외국인 +131,282주 · 기관 +93,873주 (07/15 기준)",
        "holdRatio": "28.77%",
        "streak": 4,
        "date": "07/15"
      },
      "short": {
        "ratio": 0,
        "trend": "flat",
        "comment": "공매도 미제공",
        "days": 0
      },
      "fundamentals": {
        "revGrowth": 1.7,
        "opGrowth": -27.5,
        "roe": 4.28,
        "debtRatio": 140.33,
        "opMargin": 2.78,
        "fwdEpsGrowth": 131.1,
        "years": [
          "2023.12.",
          "2024.12.",
          "2025.12.",
          "2026.12."
        ],
        "grade": "⚠️ 실적 보통",
        "gradeColor": "#ffc940",
        "comment": "실적 받침이 평범해요. 추정이익 +131% 성장 · 영업이익 -28% · ROE 4% 낮음",
        "rows": {
          "매출액": {
            "202312": 822627.0,
            "202412": 877282.0,
            "202512": 892009.0,
            "202612": 949907.0
          },
          "영업이익": {
            "202312": 36533.0,
            "202412": 34197.0,
            "202512": 24784.0,
            "202612": 42384.0
          },
          "ROE": {
            "202312": 3.69,
            "202412": 1.81,
            "202512": 4.28,
            "202612": 8.82
          },
          "부채비율": {
            "202312": 156.36,
            "202412": 160.31,
            "202512": 140.33,
            "202612": null
          }
        }
      },
      "creditRatio": 0,
      "weekly": {
        "opinion": "중립",
        "rsi": 55.8,
        "macd": 12.225,
        "macdSignal": 14.856,
        "comment": "주봉 RSI 55.8 · MACD 데드크로스"
      },
      "monthly": {
        "opinion": "중립",
        "rsi": 59.4,
        "macd": null,
        "macdSignal": null,
        "comment": "주봉 RSI 59.4 · MACD -",
        "timeframe": "월봉"
      },
      "relativeStrength": {
        "rs": -1.6,
        "comment": "KOSPI 대비 -1.6%p 약세",
        "strong": false,
        "indexLinked": false,
        "indexNote": ""
      },
      "breakout": {
        "nearHigh": false,
        "nearLow": false,
        "position": 33,
        "comment": "52주 중간 위치 (33%)"
      },
      "volSurge": {
        "surge": false,
        "ratio": 0.75,
        "comment": "거래량 평이 (0.75x)"
      },
      "news": [],
      "dart": [
        {
          "title": "기업설명회(IR)개최(안내공시)              ",
          "date": "20260707",
          "important": false,
          "corp": "LG전자",
          "url": "https://dart.fss.or.kr/dsaf001/main.do?rcpNo=20260707800184"
        },
        {
          "title": "연결재무제표기준영업(잠정)실적(공정공시)              ",
          "date": "20260707",
          "important": true,
          "corp": "LG전자",
          "url": "https://dart.fss.or.kr/dsaf001/main.do?rcpNo=20260707800176"
        },
        {
          "title": "[기재정정]사업보고서 (2025.12)",
          "date": "20260706",
          "important": false,
          "corp": "LG전자",
          "url": "https://dart.fss.or.kr/dsaf001/main.do?rcpNo=20260706000276"
        },
        {
          "title": "지속가능경영보고서등관련사항(자율공시)              ",
          "date": "20260630",
          "important": false,
          "corp": "LG전자",
          "url": "https://dart.fss.or.kr/dsaf001/main.do?rcpNo=20260630800321"
        },
        {
          "title": "임원ㆍ주요주주특정증권등소유상황보고서",
          "date": "20260611",
          "important": false,
          "corp": "LG전자",
          "url": "https://dart.fss.or.kr/dsaf001/main.do?rcpNo=20260611000049"
        }
      ],
      "basis": [
        "RSI 46.5 · Williams%R -43.3 · MFI 45.6 — 지표 중립권",
        "외국인 +131,282주 · 기관 +93,873주 · OBV 상승",
        "주봉 중립 · 33%"
      ],
      "risk": [],
      "notes": [
        "주봉·일봉 동시 매수 신호 확인 후 진입",
        "외국인 순매수 전환 시 진입 검토",
        "공매도 감소 + 거래량 증가 조합 주시"
      ],
      "noChart": false
    },
    {
      "code": "009150",
      "price": 1413000,
      "change": 153000,
      "changePct": 12.14,
      "high52w": 2417000,
      "low52w": 132500,
      "opinion": "중립",
      "score": 4,
      "source": "네이버 금융",
      "intradayFlow": null,
      "micro": null,
      "program": null,
      "flowTurnaround": false,
      "spark": [
        2200000,
        2270000,
        2228000,
        1990000,
        1964000,
        1997000,
        1993000,
        2038000,
        2184000,
        2205000,
        1926000,
        1989000,
        1828000,
        1648000,
        1479000,
        1493000,
        1584000,
        1289000,
        1260000,
        1413000
      ],
      "nuance": "관찰 구간 (소량만)",
      "buyTrack": {
        "type": "none"
      },
      "buyThreshold": {
        "buy": 5,
        "sell": -5,
        "label": "시장 우호 → 완화",
        "drivers": [
          {
            "k": "스토캐RSI",
            "v": 3
          },
          {
            "k": "MACD",
            "v": -2
          },
          {
            "k": "OBV",
            "v": -2
          },
          {
            "k": "일목",
            "v": -2
          }
        ]
      },
      "scoreDrivers": [
        {
          "k": "스토캐RSI",
          "v": 3
        },
        {
          "k": "MACD",
          "v": -2
        },
        {
          "k": "OBV",
          "v": -2
        },
        {
          "k": "일목",
          "v": -2
        }
      ],
      "macro": {
        "adj": 1.0,
        "parts": [
          "SOX +2.54% → +0.6",
          "NVDA +4.06% → +0.4"
        ]
      },
      "sigReasons": {
        "buy": [
          "스토캐스틱RSI 과매도 반등",
          "RSI 41 낮음",
          "MFI 36 낮음"
        ],
        "sell": [
          "MACD 하락(데드)",
          "OBV 하락(분산)",
          "일목 매도"
        ]
      },
      "contrarian": "",
      "profitTaking": "",
      "marginCallRisk": "",
      "turnover": "",
      "chaseWarning": "",
      "marketBrake": "",
      "flowRead": "신호는 중립이나 외국인은 5일째 매집 중이에요. │ 수급은 우호적, 지지구간 확인하며 분할 접근.",
      "tradedAt": "2026-07-15",
      "fairValue": 2470000,
      "fairValueGap": 74.8,
      "fairValueComment": "증권사 목표가 대비 74.8% 상승여력",
      "fairValueDetail": {
        "basis": "목표주가",
        "target_price": 2470000,
        "current_per": 133.47,
        "cns_per": 81.92,
        "recomm": 4.0,
        "sector": "전자부품",
        "sector_per": 18
      },
      "eps": 10587,
      "bps": 129912,
      "boll": {
        "upper": 2488487,
        "mid": 1848900,
        "lower": 1209313,
        "position": 16
      },
      "atr": {
        "atr": 212214,
        "pct": 15.02
      },
      "atrStopLoss": 988572,
      "cmf": {
        "value": -0.184,
        "comment": "분산 우세 (조용한 이탈)"
      },
      "cmfBars": [
        0.43,
        -0.19,
        -0.36,
        -0.87,
        -0.33,
        -0.5,
        -0.31,
        -0.26,
        0.41,
        -0.07,
        -0.76,
        1.0,
        -0.54,
        -0.63,
        -0.84,
        -0.11,
        -0.01,
        -0.82,
        0.16,
        0.37
      ],
      "suggestedPrice": 0,
      "suggestedLabel": "해당없음",
      "targetPrice": 0,
      "targetPrice2": 0,
      "stopLoss": 0,
      "rsi": 40.8,
      "rsiComment": "저점권",
      "macd": -6.303,
      "macdSignal": 0.792,
      "macdHist": -7.095,
      "macdComment": "데드크로스 — 하락 압력",
      "stoch": 22.1,
      "stochComment": "중립",
      "stochRsi": {
        "k": 6.7,
        "d": 5.9,
        "signal": "매수",
        "comment": "과매도 구간(7) — 반등 임박"
      },
      "divergence": null,
      "ichimoku": {
        "tenkan": 1580000,
        "kijun": 1790000,
        "senkouA": 1685000,
        "senkouB": 1612500,
        "cloudTop": 1685000,
        "cloudBot": 1612500,
        "signal": "매도",
        "comment": "구름대 아래 + 전환선<기준선 — 강한 하락 추세"
      },
      "cci": {
        "value": -114.3,
        "signal": "매수",
        "comment": "과매도(-114)"
      },
      "psar": {
        "psar": 1967948,
        "trend": "하락",
        "signal": "매도",
        "comment": "하락 추세 (저항선 ₩1,967,948)",
        "nearFlip": false
      },
      "valueSurge": {
        "ratio": 0.67,
        "surge": false,
        "comment": "거래대금 평이 (0.7배)"
      },
      "cautiousEntry": {
        "entry": false,
        "signals": [],
        "reason": "",
        "stopLoss": 0
      },
      "overheat": {
        "level": "none",
        "reasons": [],
        "color": "",
        "title": ""
      },
      "wr": -77.9,
      "wrComment": "중립",
      "mfi": 35.6,
      "mfiComment": "중립",
      "adx": {
        "adx": 47.9,
        "pdi": 13.3,
        "ndi": 37.8,
        "strength": "강한 추세"
      },
      "obv": {
        "obv": 14808992,
        "slope": -5.9,
        "trend": "하락"
      },
      "vwap": 1400324,
      "pivot": {
        "p": 1251000,
        "r1": 1339000,
        "r2": 1418000,
        "s1": 1172000,
        "s2": 1084000
      },
      "sma5": 1407800,
      "sma20": 1848900,
      "sma60": 1474767,
      "patterns": [],
      "contra": {
        "signals": [],
        "action": "현 신호 유효",
        "strength": 0
      },
      "fg": {
        "score": 42,
        "label": "중립",
        "color": "#9ab"
      },
      "ft": "외국인 2일 연속 순매수",
      "fc": "외국인 +43,342주 · 기관 +23,979주 (07/15 기준)",
      "volRatio": 0.87,
      "investor": {
        "foreign": 43342,
        "institution": 23979,
        "individual": -71849,
        "foreign5": 209283,
        "foreign20": 650594,
        "foreign60": 691465,
        "inst5": -315715,
        "inst20": -317409,
        "inst60": -751794,
        "indiv5": 104077,
        "indiv20": -307980,
        "indiv60": 89621,
        "days": 5,
        "ndays": 60,
        "daily": [
          128689,
          93871,
          -98337,
          41718,
          43342
        ],
        "flowLabel": "최근 매도 전환",
        "dailyInst": [
          -99466,
          -107789,
          -115981,
          -16458,
          23979
        ],
        "flowLabelInst": "꾸준히 매도",
        "dailyIndiv": [
          -26898,
          10819,
          215537,
          -23532,
          -71849
        ],
        "flowLabelIndiv": "최근 매수 전환",
        "foreignTrend": "외국인 2일 연속 순매수",
        "comment": "외국인 +43,342주 · 기관 +23,979주 (07/15 기준)",
        "holdRatio": "40.08%",
        "streak": 2,
        "date": "07/15"
      },
      "short": {
        "ratio": 0,
        "trend": "flat",
        "comment": "공매도 미제공",
        "days": 0
      },
      "fundamentals": {
        "revGrowth": 9.9,
        "opGrowth": 24.3,
        "roe": 7.7,
        "debtRatio": 48.98,
        "opMargin": 8.07,
        "fwdEpsGrowth": 89.6,
        "years": [
          "2023.12.",
          "2024.12.",
          "2025.12.",
          "2026.12."
        ],
        "grade": "✅ 실적 건전",
        "gradeColor": "#00e5a0",
        "comment": "실적이 주가를 받쳐줘요. 추정이익 +90% 성장 · 영업이익 +24%",
        "rows": {
          "매출액": {
            "202312": 88924.0,
            "202412": 102941.0,
            "202512": 113145.0,
            "202612": 135229.0
          },
          "영업이익": {
            "202312": 6605.0,
            "202412": 7350.0,
            "202512": 9133.0,
            "202612": 16524.0
          },
          "ROE": {
            "202312": 5.5,
            "202412": 8.16,
            "202512": 7.7,
            "202612": 13.14
          },
          "부채비율": {
            "202312": 45.17,
            "202412": 41.89,
            "202512": 48.98,
            "202612": null
          }
        }
      },
      "creditRatio": 0,
      "weekly": {
        "opinion": "중립",
        "rsi": 55.9,
        "macd": 23.664,
        "macdSignal": 24.932,
        "comment": "주봉 RSI 55.9 · MACD 데드크로스"
      },
      "monthly": {
        "opinion": "중립",
        "rsi": 67.2,
        "macd": null,
        "macdSignal": null,
        "comment": "주봉 RSI 67.2 · MACD -",
        "timeframe": "월봉"
      },
      "relativeStrength": {
        "rs": 5.9,
        "comment": "KOSPI 대비 +5.9%p 강세",
        "strong": true,
        "indexLinked": false,
        "indexNote": ""
      },
      "breakout": {
        "nearHigh": false,
        "nearLow": false,
        "position": 56,
        "comment": "52주 중간 위치 (56%)"
      },
      "volSurge": {
        "surge": false,
        "ratio": 0.87,
        "comment": "거래량 평이 (0.87x)"
      },
      "news": [],
      "dart": [],
      "basis": [
        "RSI 40.8 · Williams%R -77.9 · MFI 35.6 — 지표 중립권",
        "외국인 +43,342주 · 기관 +23,979주 · OBV 하락",
        "주봉 중립 · 56%"
      ],
      "risk": [],
      "notes": [
        "주봉·일봉 동시 매수 신호 확인 후 진입",
        "외국인 순매수 전환 시 진입 검토",
        "공매도 감소 + 거래량 증가 조합 주시"
      ],
      "noChart": false
    },
    {
      "code": "005380",
      "price": 434000,
      "change": 9500,
      "changePct": 2.24,
      "high52w": 783000,
      "low52w": 204500,
      "opinion": "중립",
      "score": -1,
      "source": "네이버 금융",
      "intradayFlow": null,
      "micro": null,
      "program": null,
      "flowTurnaround": false,
      "spark": [
        601000,
        613000,
        581000,
        511000,
        509000,
        503000,
        480500,
        497000,
        495000,
        487500,
        482000,
        492000,
        502000,
        479500,
        462500,
        445500,
        457500,
        444000,
        424500,
        434000
      ],
      "nuance": "약한 매도 우위",
      "buyTrack": {
        "type": "none"
      },
      "buyThreshold": {
        "buy": 5,
        "sell": -5,
        "label": "시장 우호 → 완화",
        "drivers": [
          {
            "k": "MACD",
            "v": -2
          },
          {
            "k": "OBV",
            "v": -2
          },
          {
            "k": "일목",
            "v": -2
          },
          {
            "k": "이격도",
            "v": 2
          }
        ]
      },
      "scoreDrivers": [
        {
          "k": "MACD",
          "v": -2
        },
        {
          "k": "OBV",
          "v": -2
        },
        {
          "k": "일목",
          "v": -2
        },
        {
          "k": "이격도",
          "v": 2
        }
      ],
      "macro": {
        "adj": 0.0,
        "parts": []
      },
      "sigReasons": {
        "buy": [
          "RSI 32 낮음",
          "MFI 38 낮음"
        ],
        "sell": [
          "MACD 하락(데드)",
          "OBV 하락(분산)",
          "일목 매도"
        ]
      },
      "contrarian": "⚡ 역발상 반등 주목 — 스토캐스틱 RSI 과매도 · RSI 저점 · 볼린저 하단",
      "profitTaking": "",
      "marginCallRisk": "",
      "turnover": "",
      "chaseWarning": "",
      "marketBrake": "",
      "flowRead": "매도 우위지만 과매도 신호가 집중돼 단기 반등 가능성이 있어요. │ 소량 분할 진입 고려, 손절선 꼭 확인.",
      "tradedAt": "2026-07-15",
      "fairValue": 802000,
      "fairValueGap": 84.8,
      "fairValueComment": "증권사 목표가 대비 84.8% 상승여력",
      "fairValueDetail": {
        "basis": "목표주가",
        "target_price": 802000,
        "current_per": 13.38,
        "cns_per": 11.14,
        "recomm": 3.96,
        "sector": "자동차",
        "sector_per": 10
      },
      "eps": 32437,
      "bps": 456242,
      "boll": {
        "upper": 595090,
        "mid": 495075,
        "lower": 395060,
        "position": 19
      },
      "atr": {
        "atr": 33857,
        "pct": 7.8
      },
      "atrStopLoss": 366286,
      "cmf": {
        "value": -0.133,
        "comment": "분산 우세 (조용한 이탈)"
      },
      "cmfBars": [
        -0.9,
        0.12,
        -1.0,
        -0.92,
        0.09,
        -0.83,
        -0.04,
        0.66,
        -0.06,
        -0.34,
        0.14,
        0.92,
        0.21,
        0.09,
        -0.42,
        -0.2,
        -0.02,
        -0.83,
        0.38,
        0.29
      ],
      "suggestedPrice": 0,
      "suggestedLabel": "해당없음",
      "targetPrice": 0,
      "targetPrice2": 0,
      "stopLoss": 0,
      "rsi": 31.6,
      "rsiComment": "저점권",
      "macd": -9.878,
      "macdSignal": -8.963,
      "macdHist": -0.915,
      "macdComment": "데드크로스 — 하락 압력",
      "stoch": 27.8,
      "stochComment": "중립",
      "stochRsi": {
        "k": 18.5,
        "d": 20.8,
        "signal": "중립",
        "comment": "K 19 / D 21"
      },
      "divergence": null,
      "ichimoku": {
        "tenkan": 458125,
        "kijun": 531125,
        "senkouA": 494625,
        "senkouB": 593125,
        "cloudTop": 593125,
        "cloudBot": 494625,
        "signal": "매도",
        "comment": "구름대 아래 + 전환선<기준선 — 강한 하락 추세"
      },
      "cci": {
        "value": -112.5,
        "signal": "매수",
        "comment": "과매도(-113)"
      },
      "psar": {
        "psar": 482000,
        "trend": "하락",
        "signal": "매도",
        "comment": "하락 추세 (저항선 ₩482,000)",
        "nearFlip": false
      },
      "valueSurge": {
        "ratio": 0.78,
        "surge": false,
        "comment": "거래대금 평이 (0.8배)"
      },
      "cautiousEntry": {
        "entry": false,
        "signals": [],
        "reason": "",
        "stopLoss": 0
      },
      "overheat": {
        "level": "none",
        "reasons": [],
        "color": "",
        "title": ""
      },
      "wr": -72.2,
      "wrComment": "중립",
      "mfi": 38.5,
      "mfiComment": "중립",
      "adx": {
        "adx": 53.7,
        "pdi": 10.0,
        "ndi": 33.2,
        "strength": "강한 추세"
      },
      "obv": {
        "obv": -3065363,
        "slope": -20.4,
        "trend": "하락"
      },
      "vwap": 440170,
      "pivot": {
        "p": 420583,
        "r1": 437917,
        "r2": 451333,
        "s1": 407167,
        "s2": 389833
      },
      "sma5": 441100,
      "sma20": 495075,
      "sma60": 579508,
      "patterns": [
        {
          "name": "도지",
          "type": "반전경고",
          "color": "#ffd166"
        }
      ],
      "contra": {
        "signals": [],
        "action": "현 신호 유효",
        "strength": 0
      },
      "fg": {
        "score": 37,
        "label": "공포",
        "color": "#ffd166"
      },
      "ft": "외국인 6일 연속 순매수",
      "fc": "외국인 +72,920주 · 기관 -71,128주 (07/15 기준)",
      "volRatio": 0.9,
      "investor": {
        "foreign": 72920,
        "institution": -71128,
        "individual": 265,
        "foreign5": 308249,
        "foreign20": -424795,
        "foreign60": -4661563,
        "inst5": 82500,
        "inst20": -208239,
        "inst60": -404998,
        "indiv5": -354917,
        "indiv20": 662241,
        "indiv60": 4963588,
        "days": 5,
        "ndays": 60,
        "daily": [
          6753,
          136289,
          85452,
          6835,
          72920
        ],
        "flowLabel": "꾸준히 매수",
        "dailyInst": [
          67202,
          -27686,
          25664,
          88448,
          -71128
        ],
        "flowLabelInst": "꾸준히 매수",
        "dailyIndiv": [
          -67448,
          -106584,
          -107436,
          -73714,
          265
        ],
        "flowLabelIndiv": "꾸준히 매도",
        "foreignTrend": "외국인 6일 연속 순매수",
        "comment": "외국인 +72,920주 · 기관 -71,128주 (07/15 기준)",
        "holdRatio": "25.12%",
        "streak": 6,
        "date": "07/15"
      },
      "short": {
        "ratio": 0,
        "trend": "flat",
        "comment": "공매도 미제공",
        "days": 0
      },
      "fundamentals": {
        "revGrowth": 6.3,
        "opGrowth": -19.5,
        "roe": 8.41,
        "debtRatio": 188.95,
        "opMargin": 6.16,
        "fwdEpsGrowth": 10.2,
        "years": [
          "2023.12.",
          "2024.12.",
          "2025.12.",
          "2026.12."
        ],
        "grade": "⚠️ 실적 보통",
        "gradeColor": "#ffc940",
        "comment": "실적 받침이 평범해요. 영업이익 -20%",
        "rows": {
          "매출액": {
            "202312": 1626636.0,
            "202412": 1752312.0,
            "202512": 1862545.0,
            "202612": 1936543.0
          },
          "영업이익": {
            "202312": 151269.0,
            "202412": 142396.0,
            "202512": 114679.0,
            "202612": 118347.0
          },
          "ROE": {
            "202312": 13.68,
            "202412": 12.43,
            "202512": 8.41,
            "202612": 8.62
          },
          "부채비율": {
            "202312": 177.44,
            "202412": 182.52,
            "202512": 188.95,
            "202612": null
          }
        }
      },
      "creditRatio": 0,
      "weekly": {
        "opinion": "중립",
        "rsi": 43.5,
        "macd": 3.148,
        "macdSignal": 10.845,
        "comment": "주봉 RSI 43.5 · MACD 데드크로스"
      },
      "monthly": {
        "opinion": "중립",
        "rsi": 52.9,
        "macd": null,
        "macdSignal": null,
        "comment": "주봉 RSI 52.9 · MACD -",
        "timeframe": "월봉"
      },
      "relativeStrength": {
        "rs": -4.0,
        "comment": "KOSPI 대비 -4.0%p 약세",
        "strong": false,
        "indexLinked": false,
        "indexNote": ""
      },
      "breakout": {
        "nearHigh": false,
        "nearLow": false,
        "position": 40,
        "comment": "52주 중간 위치 (40%)"
      },
      "volSurge": {
        "surge": false,
        "ratio": 0.9,
        "comment": "거래량 평이 (0.9x)"
      },
      "news": [],
      "dart": [
        {
          "title": "생산중단              ",
          "date": "20260713",
          "important": false,
          "corp": "현대자동차",
          "url": "https://dart.fss.or.kr/dsaf001/main.do?rcpNo=20260713800350"
        },
        {
          "title": "특수관계인으로부터기타유가증권매수",
          "date": "20260710",
          "important": false,
          "corp": "현대자동차",
          "url": "https://dart.fss.or.kr/dsaf001/main.do?rcpNo=20260710000577"
        },
        {
          "title": "기업설명회(IR)개최(안내공시)              ",
          "date": "20260710",
          "important": false,
          "corp": "현대자동차",
          "url": "https://dart.fss.or.kr/dsaf001/main.do?rcpNo=20260710800714"
        },
        {
          "title": "풍문또는보도에대한해명(미확정)              ",
          "date": "20260703",
          "important": false,
          "corp": "현대자동차",
          "url": "https://dart.fss.or.kr/dsaf001/main.do?rcpNo=20260703801045"
        },
        {
          "title": "영업(잠정)실적(공정공시)              ",
          "date": "20260701",
          "important": true,
          "corp": "현대자동차",
          "url": "https://dart.fss.or.kr/dsaf001/main.do?rcpNo=20260701800788"
        }
      ],
      "basis": [
        "RSI 31.6 · Williams%R -72.2 · MFI 38.5 — 지표 중립권",
        "외국인 +72,920주 · 기관 -71,128주 · OBV 하락",
        "주봉 중립 · 40%"
      ],
      "risk": [],
      "notes": [
        "주봉·일봉 동시 매수 신호 확인 후 진입",
        "외국인 순매수 전환 시 진입 검토",
        "공매도 감소 + 거래량 증가 조합 주시"
      ],
      "noChart": false
    },
    {
      "code": "105560",
      "price": 181600,
      "change": 1600,
      "changePct": 0.89,
      "high52w": 194500,
      "low52w": 105800,
      "opinion": "중립",
      "score": 1,
      "source": "네이버 금융",
      "intradayFlow": null,
      "micro": null,
      "program": null,
      "flowTurnaround": false,
      "spark": [
        163100,
        158300,
        157000,
        153700,
        151800,
        151900,
        149300,
        153700,
        159000,
        158500,
        165000,
        170100,
        170900,
        173200,
        171000,
        171400,
        184400,
        186200,
        180000,
        181600
      ],
      "nuance": "관찰 — 신호 부족",
      "buyTrack": {
        "type": "none"
      },
      "buyThreshold": {
        "buy": 5,
        "sell": -5,
        "label": "시장 우호 → 완화",
        "drivers": [
          {
            "k": "MACD",
            "v": 2
          },
          {
            "k": "OBV",
            "v": 2
          },
          {
            "k": "스토캐RSI",
            "v": -2
          },
          {
            "k": "일목",
            "v": 2
          }
        ]
      },
      "scoreDrivers": [
        {
          "k": "MACD",
          "v": 2
        },
        {
          "k": "OBV",
          "v": 2
        },
        {
          "k": "스토캐RSI",
          "v": -2
        },
        {
          "k": "일목",
          "v": 2
        }
      ],
      "macro": {
        "adj": -0.2,
        "parts": [
          "美금리 -0.52% → -0.2"
        ]
      },
      "sigReasons": {
        "buy": [
          "MACD 상승(골든)",
          "OBV 상승(매집)",
          "일목 강한 매수"
        ],
        "sell": [
          "스토캐스틱RSI 과매수",
          "RSI 64 높음",
          "52주 상단(85%)"
        ]
      },
      "contrarian": "",
      "profitTaking": "",
      "marginCallRisk": "",
      "turnover": "",
      "chaseWarning": "",
      "marketBrake": "",
      "flowRead": "신호는 중립이고 외국인은 이탈 중이에요. │ 서두르지 말고 수급 방향 전환을 확인 후 대응.",
      "tradedAt": "2026-07-15",
      "fairValue": 220842,
      "fairValueGap": 21.6,
      "fairValueComment": "증권사 목표가 대비 21.6% 상승여력",
      "fairValueDetail": {
        "basis": "목표주가",
        "target_price": 220842,
        "current_per": 11.48,
        "cns_per": 9.94,
        "recomm": 4.0,
        "sector": "은행",
        "sector_per": 9
      },
      "eps": 15817,
      "bps": 167092,
      "boll": {
        "upper": 188153,
        "mid": 165505,
        "lower": 142857,
        "position": 86
      },
      "atr": {
        "atr": 9343,
        "pct": 5.14
      },
      "atrStopLoss": 162914,
      "cmf": {
        "value": -0.203,
        "comment": "분산 우세 (조용한 이탈)"
      },
      "cmfBars": [
        0.52,
        -0.39,
        0.09,
        -0.63,
        -0.26,
        -0.8,
        0.07,
        0.81,
        0.15,
        -0.01,
        -0.17,
        0.34,
        -0.44,
        0.12,
        -0.51,
        -0.39,
        0.26,
        -0.6,
        -0.92,
        -0.38
      ],
      "suggestedPrice": 0,
      "suggestedLabel": "해당없음",
      "targetPrice": 0,
      "targetPrice2": 0,
      "stopLoss": 0,
      "rsi": 64.4,
      "rsiComment": "과매수 진입",
      "macd": 3.457,
      "macdSignal": 2.257,
      "macdHist": 1.2,
      "macdComment": "골든크로스 — 상승 모멘텀",
      "stoch": 73.9,
      "stochComment": "중립",
      "stochRsi": {
        "k": 83.4,
        "d": 90.2,
        "signal": "매도",
        "comment": "과매수 구간(83) — 조정 주의"
      },
      "divergence": null,
      "ichimoku": {
        "tenkan": 179750,
        "kijun": 169750,
        "senkouA": 174750,
        "senkouB": 169750,
        "cloudTop": 174750,
        "cloudBot": 169750,
        "signal": "매수",
        "comment": "구름대 위 + 전환선>기준선 — 강한 상승 추세"
      },
      "cci": {
        "value": 106.7,
        "signal": "매도",
        "comment": "과매수(107)"
      },
      "psar": {
        "psar": 159490,
        "trend": "상승",
        "signal": "매수",
        "comment": "상승 추세 유지 (손절선 ₩159,490)",
        "nearFlip": false
      },
      "valueSurge": {
        "ratio": 1.15,
        "surge": false,
        "comment": "거래대금 평이 (1.2배)"
      },
      "cautiousEntry": {
        "entry": false,
        "signals": [],
        "reason": "",
        "stopLoss": 0
      },
      "overheat": {
        "level": "none",
        "reasons": [],
        "color": "",
        "title": ""
      },
      "wr": -26.1,
      "wrComment": "중립",
      "mfi": 55.7,
      "mfiComment": "중립",
      "adx": {
        "adx": 60.1,
        "pdi": 33.4,
        "ndi": 8.3,
        "strength": "강한 추세"
      },
      "obv": {
        "obv": 5958101,
        "slope": 205.7,
        "trend": "상승"
      },
      "vwap": 181783,
      "pivot": {
        "p": 183267,
        "r1": 186933,
        "r2": 193867,
        "s1": 176333,
        "s2": 172667
      },
      "sma5": 180720,
      "sma20": 165505,
      "sma60": 160453,
      "patterns": [],
      "contra": {
        "signals": [],
        "action": "현 신호 유효",
        "strength": 0
      },
      "fg": {
        "score": 67,
        "label": "탐욕",
        "color": "#ffd166"
      },
      "ft": "외국인 순매수",
      "fc": "외국인 +284,339주 · 기관 -273,036주 (07/15 기준)",
      "volRatio": 1.05,
      "investor": {
        "foreign": 284339,
        "institution": -273036,
        "individual": -18837,
        "foreign5": -681367,
        "foreign20": -2452833,
        "foreign60": -1748442,
        "inst5": 1029710,
        "inst20": 2947756,
        "inst60": 2886147,
        "indiv5": -351559,
        "indiv20": -455422,
        "indiv60": -1106035,
        "days": 5,
        "ndays": 60,
        "daily": [
          -575548,
          170792,
          -378291,
          -182659,
          284339
        ],
        "flowLabel": "꾸준히 매도",
        "dailyInst": [
          644493,
          174290,
          312121,
          171842,
          -273036
        ],
        "flowLabelInst": "꾸준히 매수",
        "dailyIndiv": [
          -59558,
          -349804,
          40449,
          36191,
          -18837
        ],
        "flowLabelIndiv": "최근 매수 전환",
        "foreignTrend": "외국인 순매수",
        "comment": "외국인 +284,339주 · 기관 -273,036주 (07/15 기준)",
        "holdRatio": "79.39%",
        "streak": 1,
        "date": "07/15"
      },
      "short": {
        "ratio": 0,
        "trend": "flat",
        "comment": "공매도 미제공",
        "days": 0
      },
      "fundamentals": {
        "revGrowth": -4.5,
        "opGrowth": 5.9,
        "roe": 9.98,
        "debtRatio": 1211.73,
        "opMargin": 10.49,
        "fwdEpsGrowth": 20.8,
        "years": [
          "2023.12.",
          "2024.12.",
          "2025.12.",
          "2026.12."
        ],
        "grade": "⚠️ 실적 보통",
        "gradeColor": "#ffc940",
        "comment": "실적 받침이 평범해요. 추정이익 +21% 성장 · 부채 1212%",
        "rows": {
          "매출액": {
            "202312": 775064.0,
            "202412": 850764.0,
            "202512": 812307.0,
            "202612": null
          },
          "영업이익": {
            "202312": 63850.0,
            "202412": 80453.0,
            "202512": 85177.0,
            "202612": 93655.0
          },
          "ROE": {
            "202312": 8.39,
            "202412": 8.86,
            "202512": 9.98,
            "202612": 10.93
          },
          "부채비율": {
            "202312": 1120.62,
            "202412": 1166.98,
            "202512": 1211.73,
            "202612": null
          }
        }
      },
      "creditRatio": 0,
      "weekly": {
        "opinion": "중립",
        "rsi": 62.2,
        "macd": 5.443,
        "macdSignal": 4.752,
        "comment": "주봉 RSI 62.2 · MACD 골든크로스"
      },
      "monthly": {
        "opinion": "중립",
        "rsi": 72.2,
        "macd": null,
        "macdSignal": null,
        "comment": "주봉 RSI 72.2 · MACD -",
        "timeframe": "월봉"
      },
      "relativeStrength": {
        "rs": -5.35,
        "comment": "KOSPI 대비 -5.35%p 약세",
        "strong": false,
        "indexLinked": false,
        "indexNote": ""
      },
      "breakout": {
        "nearHigh": false,
        "nearLow": false,
        "position": 85,
        "comment": "52주 중간 위치 (85%)"
      },
      "volSurge": {
        "surge": false,
        "ratio": 1.05,
        "comment": "거래량 평이 (1.05x)"
      },
      "news": [],
      "dart": [
        {
          "title": "기업설명회(IR)개최(안내공시)              ",
          "date": "20260709",
          "important": false,
          "corp": "KB금융",
          "url": "https://dart.fss.or.kr/dsaf001/main.do?rcpNo=20260709800262"
        },
        {
          "title": "증권발행실적보고서",
          "date": "20260702",
          "important": true,
          "corp": "KB금융",
          "url": "https://dart.fss.or.kr/dsaf001/main.do?rcpNo=20260702000533"
        },
        {
          "title": "투자설명서(일괄신고)",
          "date": "20260701",
          "important": false,
          "corp": "KB금융",
          "url": "https://dart.fss.or.kr/dsaf001/main.do?rcpNo=20260701000618"
        },
        {
          "title": "일괄신고추가서류",
          "date": "20260701",
          "important": false,
          "corp": "KB금융",
          "url": "https://dart.fss.or.kr/dsaf001/main.do?rcpNo=20260701000612"
        },
        {
          "title": "지속가능경영보고서등관련사항(자율공시)              ",
          "date": "20260630",
          "important": false,
          "corp": "KB금융",
          "url": "https://dart.fss.or.kr/dsaf001/main.do?rcpNo=20260630800958"
        }
      ],
      "basis": [
        "RSI 64.4 · Williams%R -26.1 · MFI 55.7 — 지표 중립권",
        "외국인 +284,339주 · 기관 -273,036주 · OBV 상승",
        "주봉 중립 · 85%"
      ],
      "risk": [],
      "notes": [
        "주봉·일봉 동시 매수 신호 확인 후 진입",
        "외국인 순매수 전환 시 진입 검토",
        "공매도 감소 + 거래량 증가 조합 주시"
      ],
      "noChart": false
    },
    {
      "code": "017670",
      "price": 85000,
      "change": 1100,
      "changePct": 1.31,
      "high52w": 139500,
      "low52w": 51400,
      "opinion": "중립",
      "score": -3,
      "source": "네이버 금융",
      "intradayFlow": null,
      "micro": null,
      "program": null,
      "flowTurnaround": false,
      "spark": [
        95900,
        94900,
        94200,
        89900,
        91000,
        91400,
        90600,
        90200,
        88400,
        88600,
        87400,
        86400,
        86200,
        85200,
        84000,
        86700,
        88700,
        85700,
        83900,
        85000
      ],
      "nuance": "매도 우위 (문턱 근접)",
      "buyTrack": {
        "type": "none"
      },
      "buyThreshold": {
        "buy": 5,
        "sell": -5,
        "label": "시장 우호 → 완화",
        "drivers": [
          {
            "k": "MACD",
            "v": -2
          },
          {
            "k": "OBV",
            "v": -2
          },
          {
            "k": "일목",
            "v": -2
          },
          {
            "k": "RSI",
            "v": 1
          }
        ]
      },
      "scoreDrivers": [
        {
          "k": "MACD",
          "v": -2
        },
        {
          "k": "OBV",
          "v": -2
        },
        {
          "k": "일목",
          "v": -2
        },
        {
          "k": "RSI",
          "v": 1
        }
      ],
      "macro": {
        "adj": 0.0,
        "parts": []
      },
      "sigReasons": {
        "buy": [
          "RSI 38 낮음",
          "MFI 30 낮음"
        ],
        "sell": [
          "MACD 하락(데드)",
          "OBV 하락(분산)",
          "일목 매도"
        ]
      },
      "contrarian": "⚡ 역발상 반등 주목 — RSI 저점 · 볼린저 하단 · Williams %R 과매도",
      "profitTaking": "",
      "marginCallRisk": "",
      "turnover": "",
      "chaseWarning": "",
      "marketBrake": "",
      "flowRead": "매도 우위지만 과매도 신호가 집중돼 단기 반등 가능성이 있어요. │ 소량 분할 진입 고려, 손절선 꼭 확인.",
      "tradedAt": "2026-07-15",
      "fairValue": 117176,
      "fairValueGap": 37.9,
      "fairValueComment": "증권사 목표가 대비 37.9% 상승여력",
      "fairValueDetail": {
        "basis": "목표주가",
        "target_price": 117176,
        "current_per": 49.82,
        "cns_per": 14.67,
        "recomm": 3.76,
        "sector": "통신",
        "sector_per": 12
      },
      "eps": 1706,
      "bps": 62371,
      "boll": {
        "upper": 95611,
        "mid": 88715,
        "lower": 81819,
        "position": 23
      },
      "atr": {
        "atr": 4186,
        "pct": 4.92
      },
      "atrStopLoss": 76628,
      "cmf": {
        "value": -0.104,
        "comment": "분산 우세 (조용한 이탈)"
      },
      "cmfBars": [
        -1.0,
        0.12,
        0.26,
        -0.9,
        0.17,
        0.4,
        0.01,
        -0.2,
        -0.95,
        0.49,
        0.33,
        0.58,
        0.47,
        -0.12,
        0.2,
        -0.24,
        -0.52,
        -0.35,
        -0.23,
        -0.62
      ],
      "suggestedPrice": 0,
      "suggestedLabel": "해당없음",
      "targetPrice": 0,
      "targetPrice2": 0,
      "stopLoss": 0,
      "rsi": 38.2,
      "rsiComment": "저점권",
      "macd": -4.368,
      "macdSignal": -4.353,
      "macdHist": -0.015,
      "macdComment": "데드크로스 — 하락 압력",
      "stoch": 21.9,
      "stochComment": "중립",
      "stochRsi": {
        "k": 53.8,
        "d": 65.4,
        "signal": "중립",
        "comment": "K 54 / D 65"
      },
      "divergence": null,
      "ichimoku": {
        "tenkan": 86250,
        "kijun": 96250,
        "senkouA": 91250,
        "senkouB": 110850,
        "cloudTop": 110850,
        "cloudBot": 91250,
        "signal": "매도",
        "comment": "구름대 아래 + 전환선<기준선 — 강한 하락 추세"
      },
      "cci": {
        "value": -75.1,
        "signal": "중립",
        "comment": "중립(-75)"
      },
      "psar": {
        "psar": 90148,
        "trend": "하락",
        "signal": "매도",
        "comment": "하락 추세 (저항선 ₩90,148)",
        "nearFlip": false
      },
      "valueSurge": {
        "ratio": 0.52,
        "surge": false,
        "comment": "거래대금 평이 (0.5배)"
      },
      "cautiousEntry": {
        "entry": false,
        "signals": [],
        "reason": "",
        "stopLoss": 0
      },
      "overheat": {
        "level": "none",
        "reasons": [],
        "color": "",
        "title": ""
      },
      "wr": -78.1,
      "wrComment": "중립",
      "mfi": 30.3,
      "mfiComment": "중립",
      "adx": {
        "adx": 36.0,
        "pdi": 12.1,
        "ndi": 25.8,
        "strength": "강한 추세"
      },
      "obv": {
        "obv": -313069,
        "slope": -89.2,
        "trend": "하락"
      },
      "vwap": 86454,
      "pivot": {
        "p": 84133,
        "r1": 85567,
        "r2": 87233,
        "s1": 82467,
        "s2": 81033
      },
      "sma5": 86000,
      "sma20": 88715,
      "sma60": 97130,
      "patterns": [],
      "contra": {
        "signals": [],
        "action": "현 신호 유효",
        "strength": 0
      },
      "fg": {
        "score": 36,
        "label": "공포",
        "color": "#ffd166"
      },
      "ft": "외국인 순매도",
      "fc": "외국인 -47,378주 · 기관 +53,840주 (07/15 기준)",
      "volRatio": 0.55,
      "investor": {
        "foreign": -47378,
        "institution": 53840,
        "individual": -6537,
        "foreign5": 644827,
        "foreign20": 2513789,
        "foreign60": -1546682,
        "inst5": -156789,
        "inst20": -967322,
        "inst60": -1924573,
        "indiv5": -485483,
        "indiv20": -1471418,
        "indiv60": 3398625,
        "days": 5,
        "ndays": 60,
        "daily": [
          440386,
          110075,
          111502,
          30242,
          -47378
        ],
        "flowLabel": "꾸준히 매수",
        "dailyInst": [
          -251588,
          -13312,
          -33313,
          87584,
          53840
        ],
        "flowLabelInst": "최근 매수 전환",
        "dailyIndiv": [
          -188159,
          -96873,
          -77422,
          -116492,
          -6537
        ],
        "flowLabelIndiv": "꾸준히 매도",
        "foreignTrend": "외국인 순매도",
        "comment": "외국인 -47,378주 · 기관 +53,840주 (07/15 기준)",
        "holdRatio": "38.42%",
        "streak": -1,
        "date": "07/15"
      },
      "short": {
        "ratio": 0,
        "trend": "flat",
        "comment": "공매도 미제공",
        "days": 0
      },
      "fundamentals": {
        "revGrowth": -4.7,
        "opGrowth": -41.1,
        "roe": 3.33,
        "debtRatio": 132.4,
        "opMargin": 6.28,
        "fwdEpsGrowth": 204.9,
        "years": [
          "2023.12.",
          "2024.12.",
          "2025.12.",
          "2026.12."
        ],
        "grade": "⚠️ 실적 보통",
        "gradeColor": "#ffc940",
        "comment": "실적 받침이 평범해요. 추정이익 +205% 성장 · 영업이익 -41% · ROE 3% 낮음",
        "rows": {
          "매출액": {
            "202312": 176085.0,
            "202412": 179406.0,
            "202512": 170992.0,
            "202612": 177620.0
          },
          "영업이익": {
            "202312": 17532.0,
            "202412": 18234.0,
            "202512": 10732.0,
            "202612": 19298.0
          },
          "ROE": {
            "202312": 9.63,
            "202412": 10.83,
            "202512": 3.33,
            "202612": 9.35
          },
          "부채비율": {
            "202312": 146.31,
            "202412": 158.0,
            "202512": 132.4,
            "202612": null
          }
        }
      },
      "creditRatio": 0,
      "weekly": {
        "opinion": "중립",
        "rsi": 49.3,
        "macd": 5.204,
        "macdSignal": 8.581,
        "comment": "주봉 RSI 49.3 · MACD 데드크로스"
      },
      "monthly": {
        "opinion": "중립",
        "rsi": 63.3,
        "macd": null,
        "macdSignal": null,
        "comment": "주봉 RSI 63.3 · MACD -",
        "timeframe": "월봉"
      },
      "relativeStrength": {
        "rs": -4.93,
        "comment": "KOSPI 대비 -4.93%p 약세",
        "strong": false,
        "indexLinked": false,
        "indexNote": ""
      },
      "breakout": {
        "nearHigh": false,
        "nearLow": false,
        "position": 38,
        "comment": "52주 중간 위치 (38%)"
      },
      "volSurge": {
        "surge": false,
        "ratio": 0.55,
        "comment": "거래량 평이 (0.55x)"
      },
      "news": [],
      "dart": [
        {
          "title": "[첨부정정]지속가능경영보고서등관련사항(자율공시)              ",
          "date": "20260715",
          "important": false,
          "corp": "SK텔레콤",
          "url": "https://dart.fss.or.kr/dsaf001/main.do?rcpNo=20260715800529"
        },
        {
          "title": "풍문또는보도에대한해명(미확정)              ",
          "date": "20260710",
          "important": false,
          "corp": "SK텔레콤",
          "url": "https://dart.fss.or.kr/dsaf001/main.do?rcpNo=20260710800296"
        },
        {
          "title": "지속가능경영보고서등관련사항(자율공시)              ",
          "date": "20260630",
          "important": false,
          "corp": "SK텔레콤",
          "url": "https://dart.fss.or.kr/dsaf001/main.do?rcpNo=20260630801073"
        },
        {
          "title": "타법인주식및출자증권취득결정              ",
          "date": "20260629",
          "important": false,
          "corp": "SK텔레콤",
          "url": "https://dart.fss.or.kr/dsaf001/main.do?rcpNo=20260629801249"
        },
        {
          "title": "장래사업ㆍ경영계획(공정공시)              ",
          "date": "20260629",
          "important": false,
          "corp": "SK텔레콤",
          "url": "https://dart.fss.or.kr/dsaf001/main.do?rcpNo=20260629800978"
        }
      ],
      "basis": [
        "RSI 38.2 · Williams%R -78.1 · MFI 30.3 — 지표 중립권",
        "외국인 -47,378주 · 기관 +53,840주 · OBV 하락",
        "주봉 중립 · 38%"
      ],
      "risk": [],
      "notes": [
        "주봉·일봉 동시 매수 신호 확인 후 진입",
        "외국인 순매수 전환 시 진입 검토",
        "공매도 감소 + 거래량 증가 조합 주시"
      ],
      "noChart": false
    },
    {
      "code": "035420",
      "price": 189600,
      "change": 6400,
      "changePct": 3.49,
      "high52w": 304000,
      "low52w": 184000,
      "opinion": "매수",
      "score": 5,
      "source": "네이버 금융",
      "intradayFlow": null,
      "micro": null,
      "program": null,
      "flowTurnaround": false,
      "spark": [
        235000,
        229500,
        222000,
        202500,
        199400,
        199700,
        196400,
        204000,
        199000,
        197400,
        199900,
        195800,
        196600,
        197200,
        192700,
        184400,
        191300,
        188000,
        183200,
        189600
      ],
      "nuance": "",
      "buyTrack": {
        "type": "confirm",
        "label": "확인 매수",
        "size": "계획 물량",
        "desc": "합산 +5점 ≥ 문턱 5 (시장 우호 → 완화)"
      },
      "buyThreshold": {
        "buy": 5,
        "sell": -5,
        "label": "시장 우호 → 완화",
        "drivers": [
          {
            "k": "강세 다이버전스",
            "v": 4
          },
          {
            "k": "MACD",
            "v": -2
          },
          {
            "k": "일목",
            "v": -2
          },
          {
            "k": "52주 위치",
            "v": 2
          }
        ]
      },
      "scoreDrivers": [
        {
          "k": "강세 다이버전스",
          "v": 4
        },
        {
          "k": "MACD",
          "v": -2
        },
        {
          "k": "일목",
          "v": -2
        },
        {
          "k": "52주 위치",
          "v": 2
        }
      ],
      "macro": {
        "adj": 0.3,
        "parts": [
          "나스닥선물 +0.45% → +0.2",
          "美금리 -0.52% → +0.2"
        ]
      },
      "sigReasons": {
        "buy": [
          "상승 다이버전스",
          "52주 저점권(5%)",
          "RSI 41 낮음"
        ],
        "sell": [
          "MACD 하락(데드)",
          "일목 매도"
        ]
      },
      "contrarian": "",
      "profitTaking": "",
      "marginCallRisk": "",
      "turnover": "",
      "chaseWarning": "",
      "marketBrake": "",
      "flowRead": "신호·외국인 수급 모두 매수 우위로 방향이 일치해요. │ 신뢰도 높은 편, 지지구간 분할매수로 접근.",
      "tradedAt": "2026-07-15",
      "fairValue": 330143,
      "fairValueGap": 74.1,
      "fairValueComment": "증권사 목표가 대비 74.1% 상승여력",
      "fairValueDetail": {
        "basis": "목표주가",
        "target_price": 330143,
        "current_per": 16.46,
        "cns_per": 15.83,
        "recomm": 4.0,
        "sector": "인터넷/플랫폼",
        "sector_per": 25
      },
      "eps": 11521,
      "bps": 196985,
      "boll": {
        "upper": 226885,
        "mid": 200180,
        "lower": 173475,
        "position": 30
      },
      "atr": {
        "atr": 9357,
        "pct": 4.94
      },
      "atrStopLoss": 170886,
      "cmf": {
        "value": -0.319,
        "comment": "분산 우세 (조용한 이탈)"
      },
      "cmfBars": [
        -0.71,
        -0.49,
        -1.0,
        -0.89,
        -0.14,
        -0.95,
        0.14,
        0.72,
        -0.91,
        -0.13,
        0.32,
        0.0,
        -0.26,
        0.3,
        -0.28,
        -0.91,
        0.2,
        -0.64,
        -0.49,
        -0.05
      ],
      "suggestedPrice": 189600,
      "suggestedLabel": "매수 추천가",
      "targetPrice": 204768,
      "targetPrice2": 192867,
      "stopLoss": 179733,
      "rsi": 40.7,
      "rsiComment": "저점권",
      "macd": -5.325,
      "macdSignal": -4.858,
      "macdHist": -0.467,
      "macdComment": "데드크로스 — 하락 압력",
      "stoch": 34.1,
      "stochComment": "중립",
      "stochRsi": {
        "k": 50.9,
        "d": 45.4,
        "signal": "중립",
        "comment": "K 51 / D 45"
      },
      "divergence": {
        "bullish": true,
        "bearish": false,
        "signal": "매수",
        "comment": "강세 다이버전스 — 주가 ↓ / RSI ↑ (35→36). 바닥권 반등 신호"
      },
      "ichimoku": {
        "tenkan": 191050,
        "kijun": 223300,
        "senkouA": 207175,
        "senkouB": 242550,
        "cloudTop": 242550,
        "cloudBot": 207175,
        "signal": "매도",
        "comment": "구름대 아래 + 전환선<기준선 — 강한 하락 추세"
      },
      "cci": {
        "value": -77.5,
        "signal": "중립",
        "comment": "중립(-78)"
      },
      "psar": {
        "psar": 201442,
        "trend": "하락",
        "signal": "매도",
        "comment": "하락 추세 (저항선 ₩201,442)",
        "nearFlip": false
      },
      "valueSurge": {
        "ratio": 0.59,
        "surge": false,
        "comment": "거래대금 평이 (0.6배)"
      },
      "cautiousEntry": {
        "entry": false,
        "signals": [],
        "reason": "",
        "stopLoss": 0
      },
      "overheat": {
        "level": "none",
        "reasons": [],
        "color": "",
        "title": ""
      },
      "wr": -65.9,
      "wrComment": "중립",
      "mfi": 38.0,
      "mfiComment": "중립",
      "adx": {
        "adx": 49.8,
        "pdi": 8.2,
        "ndi": 24.6,
        "strength": "강한 추세"
      },
      "obv": {
        "obv": 19350265,
        "slope": -1.3,
        "trend": "하락"
      },
      "vwap": 188100,
      "pivot": {
        "p": 184567,
        "r1": 188033,
        "r2": 192867,
        "s1": 179733,
        "s2": 176267
      },
      "sma5": 187300,
      "sma20": 200180,
      "sma60": 215067,
      "patterns": [],
      "contra": {
        "signals": [],
        "action": "현 신호 유효",
        "strength": 0
      },
      "fg": {
        "score": 46,
        "label": "중립",
        "color": "#9ab"
      },
      "ft": "외국인 4일 연속 순매수",
      "fc": "외국인 +162,875주 · 기관 -67,672주 (07/15 기준)",
      "volRatio": 0.65,
      "investor": {
        "foreign": 162875,
        "institution": -67672,
        "individual": -92419,
        "foreign5": 434816,
        "foreign20": 951796,
        "foreign60": -3796404,
        "inst5": -106359,
        "inst20": -520419,
        "inst60": 1672522,
        "indiv5": -334882,
        "indiv20": -462581,
        "indiv60": 2019600,
        "days": 5,
        "ndays": 60,
        "daily": [
          -19693,
          192839,
          45481,
          53314,
          162875
        ],
        "flowLabel": "꾸준히 매수",
        "dailyInst": [
          -73902,
          16049,
          24025,
          -4859,
          -67672
        ],
        "flowLabelInst": "꾸준히 매도",
        "dailyIndiv": [
          119780,
          -246692,
          -57126,
          -58425,
          -92419
        ],
        "flowLabelIndiv": "꾸준히 매도",
        "foreignTrend": "외국인 4일 연속 순매수",
        "comment": "외국인 +162,875주 · 기관 -67,672주 (07/15 기준)",
        "holdRatio": "35.13%",
        "streak": 4,
        "date": "07/15"
      },
      "short": {
        "ratio": 0,
        "trend": "flat",
        "comment": "공매도 미제공",
        "days": 0
      },
      "fundamentals": {
        "revGrowth": 12.1,
        "opGrowth": 11.6,
        "roe": 7.36,
        "debtRatio": 41.9,
        "opMargin": 18.35,
        "fwdEpsGrowth": -3.2,
        "years": [
          "2023.12.",
          "2024.12.",
          "2025.12.",
          "2026.12."
        ],
        "grade": "⚠️ 실적 보통",
        "gradeColor": "#ffc940",
        "comment": "실적 받침이 평범해요. 추정이익 -3% 역성장 · 영업이익 +12%",
        "rows": {
          "매출액": {
            "202312": 96706.0,
            "202412": 107377.0,
            "202512": 120350.0,
            "202612": 137559.0
          },
          "영업이익": {
            "202312": 14888.0,
            "202412": 19793.0,
            "202512": 22081.0,
            "202612": 23891.0
          },
          "ROE": {
            "202312": 4.41,
            "202412": 7.9,
            "202512": 7.36,
            "202612": 6.54
          },
          "부채비율": {
            "202312": 47.45,
            "202412": 41.36,
            "202512": 41.9,
            "202612": null
          }
        }
      },
      "creditRatio": 0,
      "weekly": {
        "opinion": "중립",
        "rsi": 39.6,
        "macd": -5.675,
        "macdSignal": -3.97,
        "comment": "주봉 RSI 39.6 · MACD 데드크로스"
      },
      "monthly": {
        "opinion": "중립",
        "rsi": 48.3,
        "macd": null,
        "macdSignal": null,
        "comment": "주봉 RSI 48.3 · MACD -",
        "timeframe": "월봉"
      },
      "relativeStrength": {
        "rs": -2.75,
        "comment": "KOSPI 대비 -2.75%p 약세",
        "strong": false,
        "indexLinked": false,
        "indexNote": ""
      },
      "breakout": {
        "nearHigh": false,
        "nearLow": true,
        "position": 5,
        "comment": "52주 신저가 근접 (5%)"
      },
      "volSurge": {
        "surge": false,
        "ratio": 0.65,
        "comment": "거래량 평이 (0.65x)"
      },
      "news": [],
      "dart": [
        {
          "title": "[기재정정]주식교환ㆍ이전결정(종속회사의주요경영사항)              ",
          "date": "20260706",
          "important": false,
          "corp": "NAVER",
          "url": "https://dart.fss.or.kr/dsaf001/main.do?rcpNo=20260706800561"
        },
        {
          "title": "주식등의대량보유상황보고서(약식)",
          "date": "20260701",
          "important": false,
          "corp": "NAVER",
          "url": "https://dart.fss.or.kr/dsaf001/main.do?rcpNo=20260701000252"
        },
        {
          "title": "임원ㆍ주요주주특정증권등소유상황보고서",
          "date": "20260626",
          "important": false,
          "corp": "NAVER",
          "url": "https://dart.fss.or.kr/dsaf001/main.do?rcpNo=20260626000476"
        },
        {
          "title": "지속가능경영보고서등관련사항(자율공시)              ",
          "date": "20260625",
          "important": false,
          "corp": "NAVER",
          "url": "https://dart.fss.or.kr/dsaf001/main.do?rcpNo=20260625800114"
        },
        {
          "title": "풍문또는보도에대한해명(미확정)              ",
          "date": "20260618",
          "important": false,
          "corp": "NAVER",
          "url": "https://dart.fss.or.kr/dsaf001/main.do?rcpNo=20260618800694"
        }
      ],
      "basis": [
        "RSI 40.7 · Williams%R -65.9 · MFI 38.0 — 지표 중립권",
        "외국인 +162,875주 · 기관 -67,672주 · OBV 하락",
        "주봉 중립 · 52주 신저가 근접"
      ],
      "risk": [],
      "notes": [
        "피봇 S1 지지 확인 후 분할 매수",
        "OBV 수급 지속 확인",
        "주봉 신호 일치 시 비중 확대"
      ],
      "noChart": false
    }
  ]
}